Metadata-Version: 2.1
Name: a38-decimal
Version: 0.1.6
Summary: parse and generate Italian Fattura Elettronica
Home-page: https://github.com/gianpieropa/python-a38
Author: Be20
Author-email: web@be20.it
License: https://www.apache.org/licenses/LICENSE-2.0.html
Platform: UNKNOWN
Requires-Python: >=3.6
License-File: LICENSE
Requires-Dist: python-dateutil
Requires-Dist: pytz
Requires-Dist: asn1crypto
Requires-Dist: defusedxml
Provides-Extra: cacerts
Requires-Dist: requests ; extra == 'cacerts'
Provides-Extra: formatted_python
Requires-Dist: yapf ; extra == 'formatted_python'
Provides-Extra: html
Requires-Dist: lxml ; extra == 'html'
